[
    {
        "row": 3,
        "rowLen": 2,
        "column": 4,
        "columnLen": 2
    },
    {
        "row": 18,
        "rowLen": 5,
        "column":4,
        "columnLen":2
    },
    {
        "row": 18,
        "rowLen":5,
        "column":22,
        "columnLen":5
    },
    {
        "row": 18,
        "rowLen":5,
        "column":16,
        "columnLen":2
    },
    {
        "row": 18,
        "rowLen":5,
        "column":16,
        "columnLen":5
    },
    {
        "row": 18,
        "rowLen":5,
        "column":3,
        "columnLen":2
    },
    {
        "row": 23,
        "rowLen":3,
        "column":22,
        "columnLen":5
    },
    {
        "row": 23,
        "rowLen":3,
        "column":16,
        "columnLen":2
    },
    {
        "row": 23,
        "rowLen":3,
        "column":16,
        "columnLen":5
    },
    {
        "row": 9,
        "rowLen":2,
        "column":17,
        "columnLen":2
    },
    {
        "row": 9,
        "rowLen":2,
        "column":22,
        "columnLen":5
    },
    {
        "row": 15,
        "rowLen":2,
        "column":17,
        "columnLen":2
    },
    {
        "row": 15,
        "rowLen":2,
        "column":22,
        "columnLen":5
    },
    {
        "row": 6,
        "rowLen":2,
        "column":16,
        "columnLen":5
    },
    {
        "row": 6,
        "rowLen": 2,
        "column":3,
        "columnLen":2
    },
    {
        "row": 6,
        "rowLen": 2,
        "column": 16,
        "columnLen":5
    },
    {
        "row": 6,
        "rowLen":2,
        "column":14,
        "columnLen":2
    },
    {
        "row": 12,
        "rowLen":2,
        "column":16,
        "columnLen":5
    },
    {
        "row": 12,
        "rowLen":2,
        "column":14,
        "columnLen":2
    }
]